apsniper0673_mydataprovider-0.1.2.dist-info/licenses/LICENSE
mydataprovider/__init__.py
mydataprovider/api.py
mydataprovider/simple.py
mydataprovider/test_api.py
mydataprovider/frame/__init__.py
mydataprovider/frame/feather_manager.py
mydataprovider/frame/stock_dataframe.py
mydataprovider/frame/odi/df_odi.py
mydataprovider/frame/odi/odi_functions.py
mydataprovider/frame/ppd/__init__.py
mydataprovider/frame/ppd/convert_to_ppd_df.py
mydataprovider/frame/ppd/df_ppd.py
mydataprovider/frame/ppd/ppdps/__init__.py
mydataprovider/frame/ppd/ppdps/ppdp_baisc.py
mydataprovider/frame/ppd/ppdps/ppdp_custom.py
mydataprovider/frame/raw/__init__.py
mydataprovider/frame/raw/df_raw.py
mydataprovider/frame/raw/df_raw_krx.py
mydataprovider/frame/raw/df_raw_nxt.py
mydataprovider/frame/raw/merge_raw.py
mydataprovider/frame/raw/stock_data_handler_for_raw.py
mydataprovider/provider/__init__.py
mydataprovider/provider/stock_data_provider.py
mydataprovider/provider/rdp/__init__.py
mydataprovider/provider/rdp/realtime_dataframe_provider.py
mydataprovider/provider/rdp/flask/__init__.py
mydataprovider/provider/rdp/flask/rdf_client.py
mydataprovider/provider/rdp/flask/rdf_server.py
mydataprovider/provider/rdp/rdf/__init__.py
mydataprovider/provider/rdp/rdf/df_rdf.py
mydataprovider/provider/web/__init__.py
mydataprovider/provider/web/web_data_provider.py
mydataprovider/provider/web/krx/__init__.py
mydataprovider/provider/web/krx/krx_data_provider.py
mydataprovider/provider/web/naver/__init__.py
mydataprovider/provider/web/naver/naver_data_provider.py
mydataprovider/provider/web/naver/flask/__init__.py
mydataprovider/provider/web/naver/flask/naver_data_client.py
mydataprovider/provider/web/naver/flask/naver_data_fetcher.py
mydataprovider/provider/web/naver/flask/naver_data_server.py
mydataprovider/table/__init__.py
mydataprovider/table/db_with_sql.py
mydataprovider/table/stock_table_manager.py
mydataprovider/table/tm_odi.py
mydataprovider/table/tm_raw_krx.py
mydataprovider/table/tm_raw_nxt.py
mydataprovider/utility/__init__.py
apsniper0673_mydataprovider-0.1.2.dist-info/METADATA
apsniper0673_mydataprovider-0.1.2.dist-info/WHEEL
apsniper0673_mydataprovider-0.1.2.dist-info/top_level.txt
apsniper0673_mydataprovider-0.1.2.dist-info/RECORD
