Metadata-Version: 2.4
Name: apsniper0673_mydataprovider
Version: 0.1.2
Summary: My mydataprovider for APSniper0673
Author: apsniper0673
Requires-Python: >=3.8
License-File: LICENSE
Dynamic: license-file
